kravatte/__init__.py
kravatte/kravatte.py
kravatte/sanse_test.py
kravatte-1.2.0.dist-info/METADATA
kravatte-1.2.0.dist-info/RECORD
kravatte-1.2.0.dist-info/WHEEL
kravatte-1.2.0.dist-info/top_level.txt
