Metadata-Version: 2.1
Name: kravatte
Version: 1.2.0
Summary: Kravatte Encryption Authentication Tools
Home-page: https://github.com/inmcm/kravatte
Author: Michael Calvin McCoy
Author-email: calvin.mccoy@protonmail.com
License: MIT license
Download-URL: https://github.com/inmcm/kravatte/archive/1.2.0.tar.gz
Keywords: kravatte,farfalle,PRF,AEAD,MAC,crypto,encryption
Platform: UNKNOWN
Classifier: Development Status :: 4 - Beta
Classifier: Intended Audience :: Developers
Classifier: License :: OSI Approved :: MIT License
Classifier: Topic :: Security :: Cryptography
Classifier: Natural Language :: English
Classifier: Programming Language :: Python :: 3
Classifier: Programming Language :: Python :: 3.5
Classifier: Programming Language :: Python :: 3.6
Requires-Dist: numpy (>=1.12.0)
